{
  "uid": {
    "__TYPE__": "UIDContent",
    "value": "world"
  },
  "title": {
    "__TYPE__": "StructuredTextContent",
    "value": [
      {
        "type": "heading1",
        "content": {
          "text": "Police"
        }
      }
    ]
  },
  "slices": {
    "__TYPE__": "SliceContentType",
    "value": [
      {
        "key": "image$715750be-367d-4043-aa17-580e055a58a4",
        "name": "image",
        "widget": {
          "__TYPE__": "SharedSliceContent",
          "variation": "default",
          "primary": {
            "image": {
              "__TYPE__": "ImageContent",
              "origin": {
                "id": "main",
                "url": "https://images.unsplash.com/photo-1498050108023-c5249f4df085",
                "width": 3882,
                "height": 2584
              },
              "url": "https://images.unsplash.com/photo-1498050108023-c5249f4df085",
              "width": 3882,
              "height": 2584,
              "edit": {
                "zoom": 1,
                "crop": {
                  "x": 0,
                  "y": 0
                },
                "background": "transparent"
              },
              "thumbnails": {}
            },
            "caption": {
              "__TYPE__": "StructuredTextContent",
              "value": [
                {
                  "type": "paragraph",
                  "content": {
                    "text": "Minim cillum pariatur ex. Incididunt velit laboris in est enim duis anim Lorem. Non non aute nostrud incididunt amet consectetur."
                  }
                }
              ]
            }
          },
          "items": [
            {
              "__TYPE__": "GroupItemContent",
              "value": []
            }
          ]
        }
      },
      {
        "key": "quote$89b99627-d2e9-431a-bfa4-7cffe5f11fa6",
        "name": "quote",
        "widget": {
          "__TYPE__": "SharedSliceContent",
          "variation": "default",
          "primary": {
            "quote": {
              "__TYPE__": "StructuredTextContent",
              "value": [
                {
                  "type": "heading2",
                  "content": {
                    "text": "Watch"
                  }
                }
              ]
            },
            "source": {
              "__TYPE__": "FieldContent",
              "value": "being",
              "type": "Text"
            }
          },
          "items": [
            {
              "__TYPE__": "GroupItemContent",
              "value": []
            }
          ]
        }
      },
      {
        "key": "text$8c391e10-cf88-4be2-9515-2908abdde575",
        "name": "text",
        "widget": {
          "__TYPE__": "SharedSliceContent",
          "variation": "default",
          "primary": {
            "text": {
              "__TYPE__": "StructuredTextContent",
              "value": [
                {
                  "type": "paragraph",
                  "content": {
                    "text": "Id aute exercitation proident. Ad et sunt ullamco nulla consectetur Lorem eu enim qui incididunt sit ipsum ad. Voluptate esse tempor tempor amet ex ut incididunt nulla laboris occaecat tempor exercitation cupidatat mollit anim."
                  }
                }
              ]
            }
          },
          "items": [
            {
              "__TYPE__": "GroupItemContent",
              "value": []
            }
          ]
        }
      },
      {
        "key": "article_lists$84d2df62-7738-4b1a-9d5e-60e77b654076",
        "name": "article_lists",
        "widget": {
          "__TYPE__": "SharedSliceContent",
          "variation": "default",
          "primary": {},
          "items": [
            {
              "__TYPE__": "GroupItemContent",
              "value": []
            }
          ]
        }
      },
      {
        "key": "imageTextAndButton$649237e4-1cbc-4a3a-a470-2b4014cbe04d",
        "name": "imageTextAndButton",
        "widget": {
          "__TYPE__": "SharedSliceContent",
          "variation": "default",
          "primary": {
            "header_image": {
              "__TYPE__": "ImageContent",
              "origin": {
                "id": "main",
                "url": "https://images.unsplash.com/photo-1547394765-185e1e68f34e",
                "width": 6000,
                "height": 4000
              },
              "url": "https://images.unsplash.com/photo-1547394765-185e1e68f34e",
              "width": 6000,
              "height": 4000,
              "edit": {
                "zoom": 1,
                "crop": {
                  "x": 0,
                  "y": 0
                },
                "background": "transparent"
              },
              "thumbnails": {}
            },
            "small_title": {
              "__TYPE__": "StructuredTextContent",
              "value": [
                {
                  "type": "paragraph",
                  "content": {
                    "text": "Nostrud aliquip fugiat occaecat sunt reprehenderit duis id duis sit voluptate elit cillum labore ut sint. Reprehenderit aliqua laboris eiusmod reprehenderit qui veniam."
                  }
                }
              ]
            },
            "title": {
              "__TYPE__": "StructuredTextContent",
              "value": [
                {
                  "type": "paragraph",
                  "content": {
                    "text": "Anim esse adipisicing cupidatat."
                  }
                }
              ]
            },
            "button_label": {
              "__TYPE__": "FieldContent",
              "value": "globe",
              "type": "Text"
            },
            "button_link": {
              "__TYPE__": "LinkContent",
              "value": {
                "__TYPE__": "ExternalLink",
                "url": "https://slicemachine.dev"
              }
            },
            "image": {
              "__TYPE__": "ImageContent",
              "origin": {
                "id": "main",
                "url": "https://images.unsplash.com/photo-1544731612-de7f96afe55f",
                "width": 6000,
                "height": 4000
              },
              "url": "https://images.unsplash.com/photo-1544731612-de7f96afe55f",
              "width": 6000,
              "height": 4000,
              "edit": {
                "zoom": 1,
                "crop": {
                  "x": 0,
                  "y": 0
                },
                "background": "transparent"
              },
              "thumbnails": {}
            },
            "color_de_fondo": {
              "__TYPE__": "FieldContent",
              "value": "Celeste",
              "type": "Select"
            },
            "opacidad_de_fondo": {
              "__TYPE__": "FieldContent",
              "value": "4",
              "type": "Select"
            },
            "color_small_title": {
              "__TYPE__": "FieldContent",
              "value": "Morado",
              "type": "Select"
            },
            "op_color_small_title": {
              "__TYPE__": "FieldContent",
              "value": "73",
              "type": "Number"
            },
            "color_title": {
              "__TYPE__": "FieldContent",
              "value": "Celeste",
              "type": "Select"
            },
            "op_color_title": {
              "__TYPE__": "FieldContent",
              "value": "70",
              "type": "Number"
            }
          },
          "items": [
            {
              "__TYPE__": "GroupItemContent",
              "value": []
            }
          ]
        }
      },
      {
        "key": "product_card$36e891b8-d33e-433a-859e-22028c80a42a",
        "name": "product_card",
        "widget": {
          "__TYPE__": "SharedSliceContent",
          "variation": "default",
          "primary": {
            "title": {
              "__TYPE__": "StructuredTextContent",
              "value": [
                {
                  "type": "heading3",
                  "content": {
                    "text": "Greatest"
                  }
                }
              ]
            },
            "description": {
              "__TYPE__": "StructuredTextContent",
              "value": [
                {
                  "type": "paragraph",
                  "content": {
                    "text": "Dolor id in id est veniam duis laborum eu consectetur et ea. Irure aute anim sint veniam nulla cupidatat ipsum. Exercitation reprehenderit nulla nulla eiusmod tempor officia."
                  }
                }
              ]
            }
          },
          "items": [
            {
              "__TYPE__": "GroupItemContent",
              "value": []
            }
          ]
        }
      },
      {
        "key": "product_card_with_price$7f71aca4-ee99-438f-8e45-66276e6d8bec",
        "name": "product_card_with_price",
        "widget": {
          "__TYPE__": "SharedSliceContent",
          "variation": "default",
          "primary": {
            "title": {
              "__TYPE__": "StructuredTextContent",
              "value": [
                {
                  "type": "heading2",
                  "content": {
                    "text": "Screen"
                  }
                }
              ]
            },
            "description": {
              "__TYPE__": "StructuredTextContent",
              "value": [
                {
                  "type": "paragraph",
                  "content": {
                    "text": "Lorem consequat reprehenderit ea adipisicing cillum commodo sunt minim duis consectetur consectetur incididunt. Sint ullamco nostrud nisi esse in ipsum laborum voluptate."
                  }
                }
              ]
            }
          },
          "items": [
            {
              "__TYPE__": "GroupItemContent",
              "value": [
                [
                  "principal_text",
                  {
                    "__TYPE__": "FieldContent",
                    "value": "flew",
                    "type": "Text"
                  }
                ],
                [
                  "desde",
                  {
                    "__TYPE__": "FieldContent",
                    "value": "place",
                    "type": "Text"
                  }
                ],
                [
                  "link",
                  {
                    "__TYPE__": "LinkContent",
                    "value": {
                      "__TYPE__": "ExternalLink",
                      "url": "http://google.com"
                    }
                  }
                ],
                [
                  "image",
                  {
                    "__TYPE__": "ImageContent",
                    "origin": {
                      "id": "main",
                      "url": "https://images.unsplash.com/photo-1498050108023-c5249f4df085",
                      "width": 3882,
                      "height": 2584
                    },
                    "url": "https://images.unsplash.com/photo-1498050108023-c5249f4df085",
                    "width": 3882,
                    "height": 2584,
                    "edit": {
                      "zoom": 1,
                      "crop": {
                        "x": 0,
                        "y": 0
                      },
                      "background": "transparent"
                    },
                    "thumbnails": {}
                  }
                ]
              ]
            }
          ]
        }
      },
      {
        "key": "lista_destinos$48ba744d-5e13-4af4-8647-6e5dc21396ad",
        "name": "lista_destinos",
        "widget": {
          "__TYPE__": "SharedSliceContent",
          "variation": "default",
          "primary": {
            "title": {
              "__TYPE__": "StructuredTextContent",
              "value": [
                {
                  "type": "heading1",
                  "content": {
                    "text": "National"
                  }
                }
              ]
            },
            "description": {
              "__TYPE__": "StructuredTextContent",
              "value": [
                {
                  "type": "paragraph",
                  "content": {
                    "text": "Occaecat consequat do sint ad ipsum velit velit. Eu qui eu aliquip ex. Proident sint Lorem ut."
                  }
                }
              ]
            },
            "color_de_fondo": {
              "__TYPE__": "FieldContent",
              "value": "Amarillo",
              "type": "Select"
            },
            "opacidad_de_fondo": {
              "__TYPE__": "FieldContent",
              "value": "48",
              "type": "Number"
            },
            "color_de_texto": {
              "__TYPE__": "FieldContent",
              "value": "Blanco",
              "type": "Select"
            },
            "opacidad_color_de_texto": {
              "__TYPE__": "FieldContent",
              "value": "26",
              "type": "Number"
            }
          },
          "items": [
            {
              "__TYPE__": "GroupItemContent",
              "value": [
                [
                  "smalltext",
                  {
                    "__TYPE__": "FieldContent",
                    "value": "fresh",
                    "type": "Text"
                  }
                ],
                [
                  "principal_text",
                  {
                    "__TYPE__": "FieldContent",
                    "value": "capital",
                    "type": "Text"
                  }
                ],
                [
                  "image",
                  {
                    "__TYPE__": "ImageContent",
                    "origin": {
                      "id": "main",
                      "url": "https://images.unsplash.com/photo-1560762484-813fc97650a0",
                      "width": 3344,
                      "height": 2509
                    },
                    "url": "https://images.unsplash.com/photo-1560762484-813fc97650a0",
                    "width": 3344,
                    "height": 2509,
                    "edit": {
                      "zoom": 1,
                      "crop": {
                        "x": 0,
                        "y": 0
                      },
                      "background": "transparent"
                    },
                    "thumbnails": {}
                  }
                ],
                [
                  "link_route",
                  {
                    "__TYPE__": "LinkContent",
                    "value": {
                      "__TYPE__": "ExternalLink",
                      "url": "http://google.com"
                    }
                  }
                ]
              ]
            }
          ]
        }
      },
      {
        "key": "hero_section$7610fe46-3546-4314-b474-9a01a1a09d21",
        "name": "hero_section",
        "widget": {
          "__TYPE__": "SharedSliceContent",
          "variation": "default",
          "primary": {
            "titulo": {
              "__TYPE__": "FieldContent",
              "value": "shelf",
              "type": "Text"
            },
            "titulo_principal": {
              "__TYPE__": "FieldContent",
              "value": "arrangement",
              "type": "Text"
            },
            "parrafo": {
              "__TYPE__": "FieldContent",
              "value": "man",
              "type": "Text"
            },
            "texto_boton_azul": {
              "__TYPE__": "FieldContent",
              "value": "frog",
              "type": "Text"
            },
            "texto_boton_blanco": {
              "__TYPE__": "FieldContent",
              "value": "slept",
              "type": "Text"
            },
            "link_boton_azul": {
              "__TYPE__": "LinkContent",
              "value": {
                "__TYPE__": "ExternalLink",
                "url": "http://twitter.com"
              }
            },
            "link_boton_blanco": {
              "__TYPE__": "LinkContent",
              "value": {
                "__TYPE__": "ExternalLink",
                "url": "http://twitter.com"
              }
            },
            "imagen_de_fondo": {
              "__TYPE__": "ImageContent",
              "origin": {
                "id": "main",
                "url": "https://images.unsplash.com/photo-1579931794097-0ad001e51edb",
                "width": 3958,
                "height": 3958
              },
              "url": "https://images.unsplash.com/photo-1579931794097-0ad001e51edb",
              "width": 3958,
              "height": 3958,
              "edit": {
                "zoom": 1,
                "crop": {
                  "x": 0,
                  "y": 0
                },
                "background": "transparent"
              },
              "thumbnails": {}
            }
          },
          "items": [
            {
              "__TYPE__": "GroupItemContent",
              "value": []
            }
          ]
        }
      },
      {
        "key": "hero$e667bed7-c272-4358-a46e-a09842b51eb4",
        "name": "hero",
        "widget": {
          "__TYPE__": "SharedSliceContent",
          "variation": "default",
          "primary": {
            "imagen": {
              "__TYPE__": "ImageContent",
              "origin": {
                "id": "main",
                "url": "https://images.unsplash.com/photo-1586952518485-11b180e92764",
                "width": 4172,
                "height": 4000
              },
              "url": "https://images.unsplash.com/photo-1586952518485-11b180e92764",
              "width": 4172,
              "height": 4000,
              "edit": {
                "zoom": 1,
                "crop": {
                  "x": 0,
                  "y": 0
                },
                "background": "transparent"
              },
              "thumbnails": {}
            },
            "texto_boton_1": {
              "__TYPE__": "FieldContent",
              "value": "massage",
              "type": "Text"
            },
            "link_boton_1": {
              "__TYPE__": "LinkContent",
              "value": {
                "__TYPE__": "ExternalLink",
                "url": "http://google.com"
              }
            },
            "texto_boton_2": {
              "__TYPE__": "FieldContent",
              "value": "caught",
              "type": "Text"
            },
            "link_boton_2": {
              "__TYPE__": "LinkContent",
              "value": {
                "__TYPE__": "ExternalLink",
                "url": "https://slicemachine.dev"
              }
            }
          },
          "items": [
            {
              "__TYPE__": "GroupItemContent",
              "value": []
            }
          ]
        }
      },
      {
        "key": "feature1$75daa6b7-1244-4f98-869b-4f739fa49ad0",
        "name": "feature1",
        "widget": {
          "__TYPE__": "SharedSliceContent",
          "variation": "default",
          "primary": {
            "title": {
              "__TYPE__": "FieldContent",
              "value": "people",
              "type": "Text"
            },
            "image": {
              "__TYPE__": "ImageContent",
              "origin": {
                "id": "main",
                "url": "https://images.unsplash.com/photo-1448932223592-d1fc686e76ea",
                "width": 3500,
                "height": 2338
              },
              "url": "https://images.unsplash.com/photo-1448932223592-d1fc686e76ea",
              "width": 3500,
              "height": 2338,
              "edit": {
                "zoom": 1,
                "crop": {
                  "x": 0,
                  "y": 0
                },
                "background": "transparent"
              },
              "thumbnails": {}
            },
            "description": {
              "__TYPE__": "StructuredTextContent",
              "value": [
                {
                  "type": "paragraph",
                  "content": {
                    "text": "Commodo ad esse veniam nulla deserunt ipsum consequat fugiat qui sint ut. Occaecat duis officia ea aliqua do proident non sit ad Lorem ullamco. Dolore velit ullamco adipisicing ullamco laboris commodo labore cillum."
                  }
                }
              ]
            }
          },
          "items": [
            {
              "__TYPE__": "GroupItemContent",
              "value": []
            }
          ]
        }
      },
      {
        "key": "estadisticas$ed6346ab-988d-4d27-979a-8c2fdf21cf87",
        "name": "estadisticas",
        "widget": {
          "__TYPE__": "SharedSliceContent",
          "variation": "default",
          "primary": {},
          "items": [
            {
              "__TYPE__": "GroupItemContent",
              "value": [
                [
                  "numero_o_texto_principal",
                  {
                    "__TYPE__": "FieldContent",
                    "value": "wall",
                    "type": "Text"
                  }
                ],
                [
                  "descripcion",
                  {
                    "__TYPE__": "FieldContent",
                    "value": "window",
                    "type": "Text"
                  }
                ],
                [
                  "imagen",
                  {
                    "__TYPE__": "ImageContent",
                    "origin": {
                      "id": "main",
                      "url": "https://images.unsplash.com/photo-1531771686035-25f47595c87a",
                      "width": 3024,
                      "height": 3778
                    },
                    "url": "https://images.unsplash.com/photo-1531771686035-25f47595c87a",
                    "width": 3024,
                    "height": 3778,
                    "edit": {
                      "zoom": 1,
                      "crop": {
                        "x": 0,
                        "y": 0
                      },
                      "background": "transparent"
                    },
                    "thumbnails": {}
                  }
                ]
              ]
            }
          ]
        }
      },
      {
        "key": "pricing_section$819d3b72-21a4-48e3-bd34-4b1e333fa94c",
        "name": "pricing_section",
        "widget": {
          "__TYPE__": "SharedSliceContent",
          "variation": "default",
          "primary": {
            "title": {
              "__TYPE__": "FieldContent",
              "value": "average",
              "type": "Text"
            },
            "subtitle": {
              "__TYPE__": "FieldContent",
              "value": "tone",
              "type": "Text"
            }
          },
          "items": [
            {
              "__TYPE__": "GroupItemContent",
              "value": [
                [
                  "cardimage",
                  {
                    "__TYPE__": "ImageContent",
                    "origin": {
                      "id": "main",
                      "url": "https://images.unsplash.com/photo-1515378791036-0648a3ef77b2",
                      "width": 5616,
                      "height": 3744
                    },
                    "url": "https://images.unsplash.com/photo-1515378791036-0648a3ef77b2",
                    "width": 5616,
                    "height": 3744,
                    "edit": {
                      "zoom": 1,
                      "crop": {
                        "x": 0,
                        "y": 0
                      },
                      "background": "transparent"
                    },
                    "thumbnails": {}
                  }
                ],
                [
                  "cardtitle",
                  {
                    "__TYPE__": "FieldContent",
                    "value": "purpose",
                    "type": "Text"
                  }
                ],
                [
                  "cardcontent",
                  {
                    "__TYPE__": "StructuredTextContent",
                    "value": [
                      {
                        "type": "paragraph",
                        "content": {
                          "text": "Aliquip mollit occaecat id ut quis occaecat."
                        }
                      }
                    ]
                  }
                ],
                [
                  "cardbuttontext",
                  {
                    "__TYPE__": "FieldContent",
                    "value": "thrown",
                    "type": "Text"
                  }
                ],
                [
                  "cardbuttonlink",
                  {
                    "__TYPE__": "LinkContent",
                    "value": {
                      "__TYPE__": "ExternalLink",
                      "url": "https://slicemachine.dev"
                    }
                  }
                ]
              ]
            }
          ]
        }
      }
    ]
  }
}
